tripadvisorapi/__init__.py
tripadvisorapi/api.py
tripadvisorapi-1.0.0.dist-info/LICENSE.txt
tripadvisorapi-1.0.0.dist-info/METADATA
tripadvisorapi-1.0.0.dist-info/WHEEL
tripadvisorapi-1.0.0.dist-info/top_level.txt
tripadvisorapi-1.0.0.dist-info/RECORD
