Metadata-Version: 2.1
Name: tripadvisorapi
Version: 1.0.0
Summary: A simple API wrapper for the Tripadvisor Content API
Home-page: https://github.com/SK4P3/tripadvisorapi
Author: Alex Schnabl
Author-email: alex.schnabl02@gmail.com
Project-URL: Bug Tracker, https://github.com/SK4P3/tripadvisorapi/issues
Project-URL: repository, https://github.com/SK4P3/tripadvisorapi
Classifier: Programming Language :: Python :: 3
Classifier: License :: OSI Approved :: MIT License
Classifier: Operating System :: OS Independent
Requires-Python: >=3.6
License-File: LICENSE.txt
